{"content": [{"doi": "10.1007/BF02694231", "link": "http://link.springer.com//content/pdf/10.1007%2FBF02694231.pdf", "id": 0, "title": "In support of drama in early childhood education, again"}, {"doi": "10.1007/BF02694226", "link": "http://link.springer.com//content/pdf/10.1007%2FBF02694226.pdf", "id": 1, "title": "Editorial: On behalf of children"}, {"doi": "10.1007/BF02694227", "link": "http://link.springer.com//content/pdf/10.1007%2FBF02694227.pdf", "id": 2, "title": "The role of ritual in preschool settings"}, {"doi": "10.1007/BF02694228", "link": "http://link.springer.com//content/pdf/10.1007%2FBF02694228.pdf", "id": 3, "title": "Numeracy encounters in a book bag: Meeting the NCTM standards"}, {"doi": "10.1007/BF02694229", "link": "http://link.springer.com//content/pdf/10.1007%2FBF02694229.pdf", "id": 4, "title": "No Hablo Ingls: Bilingualism and multiculturalism in preschool settings"}, {"doi": "10.1007/BF02694230", "link": "http://link.springer.com//content/pdf/10.1007%2FBF02694230.pdf", "id": 5, "title": "Blurring the lines of play and work to create blended classroom learning experiences"}, {"doi": "10.1007/BF02694232", "link": "http://link.springer.com//content/pdf/10.1007%2FBF02694232.pdf", "id": 6, "title": "Technology, math, and the early learner: Models for learning"}, {"doi": "10.1007/BF02694233", "link": "http://link.springer.com//content/pdf/10.1007%2FBF02694233.pdf", "id": 7, "title": "Inclusion of children with special needs in school-age child care programs"}, {"doi": "10.1007/BF02694234", "link": "http://link.springer.com//content/pdf/10.1007%2FBF02694234.pdf", "id": 8, "title": "Preschool attendance and kindergarten readiness"}, {"doi": "10.1007/BF02694235", "link": "http://link.springer.com//content/pdf/10.1007%2FBF02694235.pdf", "id": 9, "title": "Family portfolios: Involving families in portfolio documentation"}], "entry_count": 10}